vectortiles/VERSION.md
vectortiles/__init__.py
vectortiles/mixins.py
vectortiles/settings.py
vectortiles/views.py
vectortiles/backends/__init__.py
vectortiles/backends/postgis/__init__.py
vectortiles/backends/postgis/functions.py
vectortiles/backends/python/__init__.py
vectortiles/rest_framework/__init__.py
vectortiles/rest_framework/renderers.py
vectortiles/rest_framework/views.py
django_vectortiles-1.0.2.dist-info/LICENSE
django_vectortiles-1.0.2.dist-info/METADATA
django_vectortiles-1.0.2.dist-info/WHEEL
django_vectortiles-1.0.2.dist-info/top_level.txt
django_vectortiles-1.0.2.dist-info/RECORD
