Metadata-Version: 2.1
Name: django-vectortiles
Version: 1.0.2
Summary: Django vector tile generation
Home-page: https://github.com/submarcos/django-vectortiles.git
Author: Jean-Etienne Castagnede
Classifier: Environment :: Web Environment
Classifier: Framework :: Django
Classifier: Intended Audience :: Developers
Classifier: Topic :: Internet :: WWW/HTTP
Classifier: Topic :: Internet :: WWW/HTTP :: Dynamic Content
Classifier: License :: OSI Approved :: MIT License
Classifier: Natural Language :: English
Classifier: Operating System :: OS Independent
Classifier: Development Status :: 5 - Production/Stable
Classifier: Programming Language :: Python
Classifier: Programming Language :: Python :: 3.8
Classifier: Programming Language :: Python :: 3.9
Classifier: Programming Language :: Python :: 3.10
Classifier: Programming Language :: Python :: 3.11
Requires-Python: >=3.6
License-File: LICENSE
Requires-Dist: django
Requires-Dist: mercantile
Provides-Extra: dev
Requires-Dist: factory-boy; extra == "dev"
Requires-Dist: flake8; extra == "dev"
Requires-Dist: isort; extra == "dev"
Requires-Dist: black; extra == "dev"
Requires-Dist: coverage; extra == "dev"
Requires-Dist: djangorestframework; extra == "dev"
Requires-Dist: psycopg2-binary; extra == "dev"
Requires-Dist: mapbox-vector-tile; extra == "dev"
Requires-Dist: django-debug-toolbar; extra == "dev"
Requires-Dist: sphinx-rtd-theme; extra == "dev"
Provides-Extra: mapbox
Requires-Dist: mapbox-vector-tile; extra == "mapbox"
Provides-Extra: python
Requires-Dist: mapbox-vector-tile; extra == "python"
Provides-Extra: test
Requires-Dist: factory-boy; extra == "test"
Requires-Dist: flake8; extra == "test"
Requires-Dist: isort; extra == "test"
Requires-Dist: black; extra == "test"
Requires-Dist: coverage; extra == "test"
Requires-Dist: djangorestframework; extra == "test"
Requires-Dist: psycopg2-binary; extra == "test"
